{
  "filename": "1.3.1.21.pdf",
  "subject": "Preventive Measures to contain the spread of COVID-19",
  "sr_no": "1.3.1.21",
  "policy_no": "",
  "date": "23.03.2020",
  "text": "HRay <irty TTTHNf wfetaru 7914 / Phone 91-11-25074100/25074200 (3* 4RaeT &k_TTHf HATF) Y4 Fax 91-11-25093507 25093514 National Highways Authority of India (Ministry of Road Transport and Highways) ~f-5 &a 6, #aer-10, ERaT, 7$ ferit-110075 G-5 & 6, Sector-10, Dwarka; New Delhi-110075 NHAIPolicy Matters/Administration/Establishment matters & General Instructions/2019 No 1.3.1.21 dated the March, 2020 (Chairman' $ approval vide note dated 23.03.2020) Sub: Preventive Measures to contain the spread of COVID-19. Ref: OM dated 17.03.2020 & 22.03.2020 of DoPT Government has issued instructions in above cited OMs of DoPT dated 17.03.2020 & 22.03.2020 (copies enclosed), which  may be followed. The essential/ emergency services in the context of NHA, may include safe operation & maintenance of highways, toll plazas, construction zones, etc. These may be ensured: 2 _ The operation of Toll Plazas may be continued with required/ skeletal staff by providing adequate safety measures for toll operators like   masks, gloves, goggles, sanitizers, facility for hand washing, etc: The hygiene at Toll Booths & public utilities on highways (like toilets, Hi-way Nest, Side Amenities, etc:) may be ensured & these places may be sanitized frequently. 3 ETC transactions at toll plazas should be ensured unhindered. 4_ Actions required to pr tect the interest of Govt/ NHAI may be ensured. All essential/ necessary works which are time bound  should be acted upon & decided without   delay. Those which are routine, where postponement does not involve any adverse effect, may be postponed, if CGM at HQ RO/PD decide so. 5_ In case of bids, the evaluation process may be continued by exchange of e-mails. The members of Evaluation Committee, Bidder' s &  Consultant's Representatives may attend in the process of evaluation through Video Conference/ Skypel other similar facilities. 6 _ Special precautions may be taken in case of lockdown districts and states as per directions of local administrat:on: 7_ Above examples are illustrative only, but not exhaustive. PDIRO may take appropriate decisions keeping in view the local situation and the   spirit of above instructions. If required, they may consult Member concerned. Mt M M M NHAI 23rd Way",
  "text_length": 2238,
  "extraction_method": "EasyOCR_PDF2Image",
  "used_ocr": true,
  "success": true
}