{
  "filename": "10.2.13.pdf",
  "subject": "Provision of Consulting Services for NHAI Projects ? Standard of Performance reg.",
  "sr_no": "10.2.13",
  "policy_no": "",
  "date": "27.11.2015",
  "text": "HRTy Try  TTTHNf gifeasrut &4q Phone 91-11.25074100/25074200 (s WRarv a7k <ronttf HArat4) 144/ Fax 91.11-25093507 25093514 National Highways Authority of India (Ministry of Road Transport and Highways) M-5 & 6, dqe-10, aRaw , T farif-110075 6-5 & 6, Sector-10 , Dwarka; New Delhi-110075 No.11041/218/2007-Admn Dated: 27.11.2015 PQLCY MAIIERS-Technical (186/2015) Decision Iaken in filae No NHAIINHDP V 'IMC-IIBOT/TC/pt) Sub: Provision of Consulting Services for NHAI Projects Standard of Performance reg: NHAI has been   engaging consultants for various type of works viz. preparation of  pre-feasibility reports, preparation of  Defailed Project Report, Supervision of works, Independent Engineers etc. The Consultants are expected to carry out their service in fair and tranisparent manner with equity and probity towards all stakeholders as per respective agreement and rules. 2 It has been observed that the Consultants are not always performing their roles in conformity with the envisaged responsibility. Cases hiave come t0 light where even are furnishing forged qualifying certificates, false and fictitious CVs to make their proposals responsive, submitting poor quality of DPRs without proper assessment of quantities, leading to massive variation af the time of execution of work. Also, while preparing the DPR, the Consultants are not always Surveying the project alignmert and unabie to propose suitable alternate alignments, not furnishing the proper Land Pian Schedules resulting fo abnormal variations. Also Consultants are not always proposing structural design in conformity with relevant IRC gUidelines for which there is failure of the structures affecting safety of the Highways. In Supervision Consultancy Contracts, there are instances wherein the Consultants are certifying for release of  payment for substandard work with insufficienl quality control checking, improper quantities and also issuing Provisional Completion Certificate without following the standard procedures &s per the Contraci ard llowing additiorial points for tolling without the approval of Authority . 3_ The Consultonts are required to carry ut the obligations us per the Good Industry Practice. However, failure on the part of the Consultants to discharge their duties diligently not only results in financial issues, disputes, claims but also adversely affecling the interest of Governmert, NHAI and users. 4_ There is provision in tne Contract tor  perial action eg: debarment in addition to imposition of liquidated damages &S per Contract. Besides, NHAI has issued Policy Circular (Technicai) 97/2012 dated 7.04.2014 for the procedure for deterrent penalty action against Defaulting Consultants. 5_ All the Consultirig   Firms are well experienced hoving very senior and qualified personnel empioyed with tnem; The Autherity nas all regards to Consultants who are the Representctives of the Employer in the supervision of the projects. However , there is practically no roOr for the poor performing Consultants to render services with the Authority Contd  P/2 CMMm WHA they",
  "text_length": 3077,
  "extraction_method": "EasyOCR_PDF2Image",
  "used_ocr": true,
  "success": true
}