{
  "filename": "12.5.pdf",
  "subject": "Tentative guidelines for Transverse Bar Marking at Accident Prone Spots on National Highways-reg.",
  "sr_no": "12.5",
  "policy_no": "",
  "date": "11.06.2012",
  "text": "HRdi 77cfly TTHT gifeasrot Taiq Phone ; 91-11-25074100/25074200 (aed War7 &r TTHTf TNa4) #TH / Fax 91-11-25093507 25093514 71 7 4 National Highways Authority of India (Ministry of Road Transport and Highways) 01-5 Wa 6, #de-10, ERVT, T fcrif 110 075 G-5 & 6, Sector-10, Dwarka, New Delhi-110075 No.11041/218/2007-Admn 1Imh June, 2012 PQLICY MATTERS-TECHNICAL (105/2012) (Decision taken on FileNoNHAIRRSCL2O12MMiscl Subject: -Tentative Guidelines for Transverse Bar Marking at Accident Prone Spots on National Highways-Reg: In order to address the engineering related issue for road safety at accident prone spots on National Highways, MoRT&H vide their letter No_ RWINH-33044/13/2012-S&R dated 04.05.2012 (copy enclosed) has issued guidelines for transverse bar marking: Accordingly, it has been decided to provide transverse bar marking at identified accident prone spots where the need for alerting the drivers/reduction in the speed is desired. The transverse bar marking shall be in addition to other standard markings/signages (as shown in the enclosed figure-] and annexure) as per existing guidelines/circulars. 2. Feedback on these guidelines may be sent to Road Safety Cell. 3. This issues with the approval of Chairman: 6p (V.KSharma) Chiet General Manager (Coord /LA) To, Allolticers and employees of HQ/ZO[ROS[PIUs[CMUs[Site Offices NHAL",
  "text_length": 1349,
  "extraction_method": "EasyOCR_PDF2Image",
  "used_ocr": true,
  "success": true
}