{
  "filename": "2.1.16.pdf",
  "subject": "One Time Settlement of Disputes/ claims of the Concessionaire/ Contractor through 3 CGMs Committee/ Independent Settlement Advisory Committee(ISAC).",
  "sr_no": "2.1.16",
  "policy_no": "",
  "date": "7.11.2013",
  "text": "6?, 48 TTGAIf  91feahrot Phone 91-11-25074100/25074200 sau 744 #4 Fax 91-11-25093507 25093514 4ta6a 31r '3194) National Highways Authority of India (Ministry of Road Transport and Highways) #-5 % 6, d42r-10, ET.FI, T{ Rcd-110075 10. Dwarka, New Delhi-110075 6-5 & 6, Sector-- November, 2013 NHAI/ISACIMisc /2013/ CIRCULAR /Claims of the  Concessionaire/Contractor Sub: One Time Settlement of Disputes, Settlement 'Advisory Committee through 3 CGMs' Committee/Independent (ISAC): NHAI is endeavouring to settle the 13 As you are aware that of the Contract Packages already Concessionaire Contractorse claintstiorisingougt consteutiontOdG cGMs' Committees implemented or under impleereentiodvistrougbmnittet tiGAC) ` Under this process; as well as Independent Settlement Advisory Committees which have been there is a of putting up the cases to these action for putting up cirerelated earlier. However;it i5 reiterated thatnchactioitsatrreg to be taken: for one time settlement; the following actions are these cases should be asked to subject Power %f Attorney in favourthe (a) The Claimant for negotiation/settlement with the the person who is authorized Committee on behalf of all partners of JV. Settlement should be asked to submit an  Undertaking  regarding (b) The Claimant Arbitral Tribunal, for keeping the Arbitral willingness to respective proceedings on hold: Technical Division should also supply brief details otthe C) The concerned claims and counter claims of NHAI etc claims, stand of NHAI on various are required to be completed and the one-time The above formalities SO as to enable the 3 CGMs' settlement cases should be up accordingly Committees to the case further. P.C. Grover ) CGM(Legal)_ To= AILCGMs(Technical) TYN Tr| 0erh Ref: system required put process",
  "text_length": 1780,
  "extraction_method": "EasyOCR_PDF2Image",
  "used_ocr": true,
  "success": true
}