{
  "filename": "2.7.2.pdf",
  "subject": "Fee of Arbitrators in the cases of Civil Engineering construction contracts/ supervision consultancies.",
  "sr_no": "2.7.2",
  "policy_no": "",
  "date": "31.05.2004",
  "text": "HRdfq 7rf14 <MHT wHFUT Phone 91-11-25074100/2574200 Fax 91-11-25093507/25093514 (;t 767 3 Tamnf +ATT) Extn_ 2223/2318/12468/2553: National Highways Authority of India (Ministry of Road Transport & Highways) 65&6_ Sector-10, Owarka. New Delni-110075 No: 11041/21/2002-Admn. 31 2004 POLICY MATIER L ADMINISJRATIONFINANCE {8012004) [Decision taken on DREQA Cell File No. NHAIIDRRQA CelllG: 1/2003] Sub:: Fee of Arbitrators in the cases of Civil  Engineering Construction Contracts Supervision Consultancies: In supersession to our Policy Circular No. 37/2003 dated March 27 , 2003 on the above subject; it has noi-been decided that the maximum limit for payment of fee in Arbitration cases shall be as indicated below: Sr_ Particulars Maximum amount payable per Arbitrator Arbitrator fee Rs_5,O00}- per subject ' to 3 maxintijm of Rs.1.50 lacs per case 2 Reading Charges Rs.6,000/- per arbitrator per case 3 Secretarial Assistance Rs.5,000/- per arbitrator per case_ Incidental   Charges (telephone_ fax, Rs.6,O00/- per arbitrator per Case_ postage etc:) 5 Charges for Publishingideclaration of Maximum of Rs: 10,0007- the Award Other expenses (actuals against bills Maximum cellings  subject to the   prescribed   ceiling) applicable for the days of hearing only: Traveling Expenses Economy class (By Air)+ First class AC (By and AC car (By road) Lodging and Boarding a)Rs.8,000/- per (in metro cities} bJRs.5,0007- per (in other cities) c)Rs.2,000/- per if any Arbitrator. makes their Own arrangement iii} Local Travel Rs.700/- per 2 Since the fee structure has to be agreed to by both the parties (i.e. NHAI and the Contractor Supervision Consultant), Ihe above fee structure may also be got accepted by the respective Contractors Supervision Consultants through supplementary agreement It:has also been decided that in exceptional cases; 'such as cases involving major legal implicationslwider ramifications/higher financial stakes etc. special tee structure could be fixed in consultation with the Contractor Supervision Consultants and with the specific approval of the Chairman, NHAV before appointment of the Arbitrator: Conttt; (4 \"D9 NhaL May, day . train): day- day - day: day",
  "text_length": 2184,
  "extraction_method": "EasyOCR_PDF2Image",
  "used_ocr": true,
  "success": true
}