{
  "filename": "6.35.pdf",
  "subject": "Mandatory Use of Maintenance Module of NHAI ONE Application – reg.",
  "sr_no": "6.35",
  "policy_no": "",
  "date": "09.02.2024",
  "text": "IRaly <zy TTHif giferaz<ut (Tev5 9Rde7 & rTHrf TA1T4, 4RG TTT) National Highways Authority of India HrnAa J (Ministry of Road Transport and Highways, Government of India) 611-5 Qai 6, #zr-10, &RAT, 7 fevit 110 075 G-5 & 6, Sector-10, Dwarka, New Delhi-110075 T/Phone 91-11-25074100 / 25074200 NHAI/Policy Guidelines/ IT /2024 Policy Circular No.6.35/2024 dated O9th February, 2024 {Decision taken on E-Office File No. NHAI/HO/MaintenanceModule/ NHAIONE (Comp. No. 235853)} Sub: Mandatory Use of Maintenance Module of NHAI ONE Application reg: Chairperson vide letter dated 26.10.2022, specifically directed that all the monitoring including payments of maintenance activities on Highways shall be through the 'TATPAR' App only. Subsequently, the maintenance module has been subsumed in NHAI ONE Application. 2 In this regard, it is  observed that above mentioned instructions for mandatory inspection of Projects in O&M Phase using NHAI ONE module is not being followed by AE/IE/SC and PD/RO are not being able to enforce the directive 3_ In view of the above, with approval of the Competent Authority, the following shall be ensured by PD/RO in all projects under O&M phase: 1) ROs /PDs shall ensure mandatory use of maintenance module of NHAI ONE application by all the AE/IEISC Consultants for Projects in O&M Phase_ (ii) ROs/PDs shall assess the available staff with AE/IEISC to conduct inspection through Maintenance Module of NHAI ONE app and if required, may engage one dedicated resource for this task through COS for which ROs are herewith delegated the power: The remuneration of such additional resource may be kept at par with Assistant Highway Engineer quoted in the respective consultancy assignment. (iii) It must be ensured that the inspection through NHAI ONE application is carried o daily basis. (iv) As the maintenance module of NHAI ONE application serves as a tool for measurement of the performance of the obligations of the AEZIE/SC during O&M Period of the project, the non-use of this module would trigger provision of clause 2.8 of GCC which is regarding suspension of payments for non-fulfilment of performance obligations by the consultants and thereafter clause 2.9.1(a) of GCC which refers to Termination due to continued non-performance of obligations. 4_ Further, in all new AE/IEISC consultancy projects, to be invited at RO/HQ level, the following clause under GCC Clause 2.9.1 may be inserted: \"Non-Use of Maintenance Module of NHAI ONE Application or misrepresentation of facts/figures/ photos/ videos through the module would result in deduction of 50% remuneration of all the Key-Personnel and Sub-Key Personnel Staff in first three instances.  Thereafter, on fourth such instance the Authority can terminate the Contract Agreement on Consultants Default: Contd_2I - 91 7 ? 91 NHAL NHAI,",
  "text_length": 2826,
  "extraction_method": "EasyOCR_PDF2Image",
  "used_ocr": true,
  "success": true
}