{
  "filename": "8.1.16.pdf",
  "subject": "Criteria for PPPAC approval",
  "sr_no": "8.1.16",
  "policy_no": "",
  "date": "07.01.2013",
  "text": "9Rrlv 7y THFf  uifea<ut {4I / Phone : 91-11-28070100128074700 M1 (Tg& 4Raev 3 TTHRt#r4) 4I Fax 91-11-25098507 18088810 National Highways Authority of India (Ministry of Road Transport and Highways) 4-5 & 6, darr-10, ERTT, T ferfl-110075 G-5 & 6, Sector-10, Dwarka, New Delhi-110075 NHAII1O13/DGM (LA/Coord) Circular/2013/1 Date: 07.01.2013 CIRCULAR Sub: Criteria for PPPAC approval: As per present policy regarding approval of projects by the PPPAC the following milestones should be achieved before a project is submitted for approval of PPPAC: - (iii) Notification under section 3(A) of NH Act should have been issued for atleast 90% of the land area required for the project and (iv) The total area of land in possession together with the area notified under section 3(D) of NH Act should be atleast 60% of the area required for the project. It is further stated that criterion as stated in SI, No. above together with the criterion as per S No (ii) above, are required to be met before a project is considered for PPPAC approval: All concerned are requested to take note of the above and act accordingly This is issued with the approval of Member (Admn:): +/ 9) (V.K Sharma) CGM (LA & Coord) to: AII CGM (HQ) AII ROs AIIGMs(HQ) AII PIUs 8 PS to Chairman PS to Member At RT Rt NHAI Copy",
  "text_length": 1289,
  "extraction_method": "EasyOCR_PDF2Image",
  "used_ocr": true,
  "success": true
}