{
  "filename": "8.1.15.pdf",
  "subject": "Award of Annuity Projects by NHAI",
  "sr_no": "8.1.15",
  "policy_no": "",
  "date": "21.05.2012",
  "text": "#Trrf 774ft4 <omHrf gfedrut T44 Phone 91-11-25074100/25074200 (ed5 9att &r THi #r4) # / Fax 91-11-25093507 25093514 Tt # National Highways Authority of India (Ministry of Road Transport and Highways) #ft-5 &a 6, 7qer-10, #Rra, 7 faarft _ 110 075 G-5 & 6, Sector-10, Dwarka_ New Delhi-110075 No.11041/218/2007-Admn 21st 2012 PQLCY MATERS-IECHNICAL (102/2012) (Decision taken on FileNoNHAIHEWI2008-09/isclssues (Pt)) Subject: Award of Annuily Projects by NHAI: NHAI has awarded certain annuity projects in 2009-10 and 2010-11, where, for the purpose of analyzing the reasonableness of these bids at the RFP stage, parameters such as interest rate, MAT rate, inflation factor etc. were updated to their cUrrent levels or to rates advised by MoRT&H: While seeking approval of the Authority for such awards, full information as regards the revised parameters and justification thereof was placed before the Authority and orders accordingly obtained: 2 On a review of such awards, MoRT&H is f the opinion that NHAI was not in order in testing the reasonableness of such awards based on revised/updated parameters and parameter values should remain at the same levels aS considered by PPPAC while clearing the projects. MoRT&H directed that NHAI place MoRT&H observations on such awards before the Authority. Accordingly, the matter was placed before the Authority. 3 The Authority in its 87ih meeting took note of the information placed and observed that all such projects were earlier approved by the Board after  taking the above mentioned factors (i.e. change in the parameter values to ascertain to reasonableness of relative bids) fully into consideration. The Authority also observed that decision to award such projects have been taken by the Board having due regard to all these factors and no further  approvals are   required: The Board directed that in future , where base parameters are changed after getting approval of the PPPAC and if this affects the project evaluation, the matter should be once again taken Up to the PPPAC. 4 AlI are requested to note the  aforesaid directions of the Authority for future guidance. 5 This issues with the approval of Chairman: 2 | (V.K.Sharma) Chief General Manager (Coord./LA) To, Allofficers andemployees ot HQIZO[ROs[PIUs[CMUs/Site Offices NT 71 NHAL May,",
  "text_length": 2304,
  "extraction_method": "EasyOCR_PDF2Image",
  "used_ocr": true,
  "success": true
}